odoo10_addon_website_event_excerpt_img-10.0.1.0.0-py2.7-nspkg.pth
odoo/addons/website_event_excerpt_img/README.rst
odoo/addons/website_event_excerpt_img/__init__.py
odoo/addons/website_event_excerpt_img/__manifest__.py
odoo/addons/website_event_excerpt_img/i18n/es.po
odoo/addons/website_event_excerpt_img/images/backend.png
odoo/addons/website_event_excerpt_img/images/customize.png
odoo/addons/website_event_excerpt_img/images/frontend.png
odoo/addons/website_event_excerpt_img/models/__init__.py
odoo/addons/website_event_excerpt_img/models/event.py
odoo/addons/website_event_excerpt_img/static/description/icon.png
odoo/addons/website_event_excerpt_img/static/src/css/website_event_excerpt_img.css
odoo/addons/website_event_excerpt_img/static/src/css/website_event_excerpt_img.css.map
odoo/addons/website_event_excerpt_img/static/src/css/website_event_excerpt_img.sass
odoo/addons/website_event_excerpt_img/views/assets.xml
odoo/addons/website_event_excerpt_img/views/event.xml
odoo/addons/website_event_excerpt_img/views/event_event_view.xml
odoo10_addon_website_event_excerpt_img-10.0.1.0.0.dist-info/DESCRIPTION.rst
odoo10_addon_website_event_excerpt_img-10.0.1.0.0.dist-info/METADATA
odoo10_addon_website_event_excerpt_img-10.0.1.0.0.dist-info/RECORD
odoo10_addon_website_event_excerpt_img-10.0.1.0.0.dist-info/WHEEL
odoo10_addon_website_event_excerpt_img-10.0.1.0.0.dist-info/metadata.json
odoo10_addon_website_event_excerpt_img-10.0.1.0.0.dist-info/namespace_packages.txt
odoo10_addon_website_event_excerpt_img-10.0.1.0.0.dist-info/top_level.txt
